luce_otp-0.1.1.dist-info/METADATA
luce_otp-0.1.1.dist-info/WHEEL
luce_otp/__init__.py
luce_otp/luce_otp.cpython-311-darwin.so
luce_otp-0.1.1.dist-info/RECORD
