Metadata-Version: 2.3
Name: luce_otp
Version: 0.1.1
Classifier: Programming Language :: Python
Classifier: Programming Language :: Python :: 3
Classifier: Programming Language :: Rust
Classifier: License :: OSI Approved :: MIT License
Classifier: Operating System :: OS Independent
Summary: A Python package for zero-knowledge OTP proof using Rust and Groth16 zk-SNARKs
Keywords: zk-SNARK,OTP,zero-knowledge,Rust,Python,Maturin
Author-email: Ankur Lohachab <ankur.lohachab@maastrichtuniversity.nl>
License: MIT
Requires-Python: >=3.6
